{"success":true,"boosters":[{"_id":"5c197fadc8f245280926413d","purchaserUuid":"978ddb705a8e43618e41749178c020b0","amount":2,"originalLength":3600,"length":3595,"gameType":24,"stacked":true,"dateActivated":1545244519133},{"_id":"5e8c92270cf287986cd00dbf","purchaserUuid":"dfe1bb0a4220421486506ba487cdb530","amount":3,"originalLength":3600,"length":3600,"gameType":23,"dateActivated":1586351429371,"stacked":true},{"_id":"552613eb0cf2ecda544e0ccd","purchaserUuid":"0113a2aba768477baa4a566f0f093a64","amount":2,"originalLength":1800,"length":1800,"gameType":23,"dateActivated":1626200192810,"stacked":true},{"_id":"62e522a30cf2beec62b0491a","purchaserUuid":"b29172f9554f4779b8d54ca600f17d9a","amount":2.1,"originalLength":3600,"length":3336,"gameType":51,"dateActivated":1659918923976,"stacked":["a0a28e11-2648-4b5d-8175-e250be753704"]},{"_id":"62f0a3900cf2beec62b093f8","purchaserUuid":"504efc26a1c446e5a5c6a72340ab8add","amount":2,"originalLength":3600,"length":3600,"gameType":51,"dateActivated":1659937721003},{"_id":"62ef6b240cf2beec62b08bc6","purchaserUuid":"0a89f3c27dfa4057924cc74db86c32bb","amount":2,"originalLength":3600,"length":3600,"gameType":51,"dateActivated":1659958347973},{"_id":"62bf28510cf252bc6408df50","purchaserUuid":"b15a7da3209e4f88939b6c6cbb1b89a1","amount":2,"originalLength":3600,"length":3600,"gameType":51,"dateActivated":1659962424161},{"_id":"62f1057f0cf252bc64092a60","purchaserUuid":"1c42243b7e634a02b5df37b55c60fea1","amount":2,"originalLength":3600,"length":3600,"gameType":51,"dateActivated":1659962902751},{"_id":"62f10fa60cf252bc64092a86","purchaserUuid":"62d9907aae234e76b7361ea59ba18ea0","amount":2,"originalLength":3600,"length":3600,"gameType":51,"dateActivated":1659966470201},{"_id":"62e522a30cf2beec62b04919","purchaserUuid":"b29172f9554f4779b8d54ca600f17d9a","amount":2,"originalLength":3600,"length":3600,"gameType":51,"dateActivated":1659967362370},{"_id":"62f118c80cf252bc64092a95","purchaserUuid":"3715015beb644d21ad1fb49b4c857fec","amount":2,"originalLength":3600,"length":3600,"gameType":51,"dateActivated":1659967756638},{"_id":"62de5d320cf2beec62b02061","purchaserUuid":"96875f56ce054e318a6b224d5f3a8ad2","amount":2,"originalLength":3600,"length":3600,"gameType":51,"dateActivated":1659967891149},{"_id":"62db6a460cf2beec62b00d26","purchaserUuid":"9b5235e7a6aa4be690921292eee36ab2","amount":2,"originalLength":3600,"length":3600,"gameType":51,"dateActivated":1659969064592},{"_id":"62e2bb2e0cf252bc64091660","purchaserUuid":"2c7ae7c461804ccd89f05809d02d333c","amount":2,"originalLength":3600,"length":3600,"gameType":51,"dateActivated":1659969235139},{"_id":"62f0ea1c0cf2beec62b094e4","purchaserUuid":"aa340d20e1034a969cc8bdbdaf13fd87","amount":2,"originalLength":3600,"length":3600,"gameType":51,"dateActivated":1659972194842},{"_id":"5fe06cce44f4c0135746d657","purchaserUuid":"db3fdc44d41b45e09e952dca1ba02b56","amount":2,"originalLength":3600,"length":3600,"gameType":51,"dateActivated":1659973140210},{"_id":"6275f5200cf225808cb3ffb0","purchaserUuid":"e92906a3e7dd42a9939045542d7e3245","amount":2,"originalLength":3600,"length":3600,"gameType":51,"dateActivated":1659975059435},{"_id":"62f137920cf2a3bd9b16dc84","purchaserUuid":"68b9ea28989f46469c8e373a21fea7a6","amount":2,"originalLength":3600,"length":3600,"gameType":51,"dateActivated":1659975866846},{"_id":"61d8f15a0cf26d6213bbd2f1","purchaserUuid":"54f4c7e3b67048dd94badf8cac8d00c1","amount":2,"originalLength":3600,"length":3600,"gameType":51,"dateActivated":1659976201934},{"_id":"62e805270cf2beec62b05cb7","purchaserUuid":"0480da6c47ba4dffa790794d3089e2b4","amount":2,"originalLength":3600,"length":3600,"gameType":51,"dateActivated":1659981526796},{"_id":"62f1565f0cf252bc64092b1c","purchaserUuid":"930e1055e0ca422889bd582ba5e536bd","amount":2,"originalLength":3600,"length":3600,"gameType":51,"dateActivated":1659983481600},{"_id":"62f13c7e0cf2a3bd9b16dcc6","purchaserUuid":"c165e45738bd45d99df41274cdb68166","amount":2,"originalLength":3600,"length":3600,"gameType":51,"dateActivated":1659984124238},{"_id":"62f106690cf252bc64092a67","purchaserUuid":"cbe7af2b61da46e3aa7d3da39bd5b9b3","amount":2,"originalLength":3600,"length":3600,"gameType":51,"dateActivated":1659986749575},{"_id":"62cae53f0cf252bc6408f062","purchaserUuid":"25fcb12901c444a08576da6538f460a6","amount":2,"originalLength":3600,"length":3600,"gameType":51,"dateActivated":1659987216958},{"_id":"62f161860cf2a3bd9b16dd9f","purchaserUuid":"f6da3812a70b40c4a6600705afa3671f","amount":2,"originalLength":3600,"length":3600,"gameType":51,"dateActivated":1659988315291},{"_id":"62bc643a0cf2beec62af2e6f","purchaserUuid":"c250b780444649f7b16e983cdfc3a69f","amount":2,"originalLength":3600,"length":3600,"gameType":51,"dateActivated":1659996446472},{"_id":"60295a9a44f4c4e13fc143aa","purchaserUuid":"4830ebdbf0be4de3a49aa6cf96991e97","amount":2,"originalLength":3600,"length":3600,"gameType":51,"dateActivated":1660007382996},{"_id":"62ee4dfd0cf252bc6409269d","purchaserUuid":"14c5cf8c4a4b4c8fa62fbce6fff3255a","amount":2,"originalLength":3600,"length":3600,"gameType":51,"dateActivated":1660010362289},{"_id":"60dd06040cf25edf42c8b33d","purchaserUuid":"06777508a0144cbdaa3c179758b5e277","amount":2,"originalLength":3600,"length":3600,"gameType":51,"dateActivated":1660010575674},{"_id":"62c8179d0cf252bc6408ec1d","purchaserUuid":"bb8496084c1e448c862cb68f350fa25c","amount":2,"originalLength":3600,"length":3600,"gameType":51,"dateActivated":1660016327921},{"_id":"62f161860cf2a3bd9b16dd9e","purchaserUuid":"f6da3812a70b40c4a6600705afa3671f","amount":2,"originalLength":3600,"length":3600,"gameType":51,"dateActivated":1660026097652},{"_id":"62ec94cf0cf2beec62b07959","purchaserUuid":"cb9a31aea8a642d2a7745d58f26cc9c6","amount":2,"originalLength":3600,"length":3600,"gameType":51,"dateActivated":1660032899135},{"_id":"62f036d00cf2beec62b09143","purchaserUuid":"9e7fb26ed2a84e14b508a4be92d432b3","amount":2,"originalLength":3600,"length":3600,"gameType":51,"dateActivated":1660034422678},{"_id":"62f0a3900cf2beec62b093f7","purchaserUuid":"504efc26a1c446e5a5c6a72340ab8add","amount":2,"originalLength":3600,"length":3600,"gameType":51,"dateActivated":1660037185998},{"_id":"62f22ce40cf252bc64092c37","purchaserUuid":"4038dac009394bbea6d598e0aa310e52","amount":2,"originalLength":3600,"length":3600,"gameType":51,"dateActivated":1660038969092},{"_id":"62f12d720cf252bc64092ae2","purchaserUuid":"abb9005915e142829c9dc7ee906ca513","amount":2,"originalLength":3600,"length":3600,"gameType":51,"dateActivated":1660040812007},{"_id":"62f237610cf252bc64092c48","purchaserUuid":"6ebbe6d9a0eb43a7ab26621ba22303df","amount":2,"originalLength":3600,"length":3600,"gameType":51,"dateActivated":1660041156003},{"_id":"62d051ed0cf252bc6408f970","purchaserUuid":"85ccca05e38346cdb1ea2afced1ea8be","amount":2,"originalLength":3600,"length":3600,"gameType":51,"dateActivated":1660042260265},{"_id":"62f1706f0cf252bc64092b48","purchaserUuid":"07e1d8ea7e694aaabaf2fb66c3927024","amount":2,"originalLength":3600,"length":3600,"gameType":51,"dateActivated":1660046583489},{"_id":"62dba5920cf2beec62b00ea0","purchaserUuid":"c2bbfc403ca44480a16fe0586e94bc95","amount":2,"originalLength":3600,"length":3600,"gameType":51,"dateActivated":1660046839754},{"_id":"62f22d6e0cf2a3bd9b16e1c3","purchaserUuid":"44421e7a5ffb409bb01c19a4ec59cfa9","amount":2,"originalLength":3600,"length":3600,"gameType":51,"dateActivated":1660046900555},{"_id":"62eea6bc0cf2beec62b08631","purchaserUuid":"09efc71583fc4440ad0a40069b0388eb","amount":2,"originalLength":3600,"length":3600,"gameType":51,"dateActivated":1660054303946},{"_id":"62f27d960cf2a3bd9b16e3ab","purchaserUuid":"42951d945c3f4be29df42e36970b0741","amount":2,"originalLength":3600,"length":3600,"gameType":51,"dateActivated":1660059565517},{"_id":"62f13c420cf2a3bd9b16dcb2","purchaserUuid":"e9becc5e11f64485a62f10c9dffa5f5b","amount":2,"originalLength":3600,"length":3600,"gameType":51,"dateActivated":1660061783575},{"_id":"62f16f4d0cf252bc64092b3f","purchaserUuid":"beade9198d3d4ffb967e5e3ca46a1edf","amount":2.2,"originalLength":3600,"length":2217,"gameType":13,"dateActivated":1660062861696,"stacked":["144abc37-63ec-41d7-9974-70c8d8969869","a0a28e11-2648-4b5d-8175-e250be753704"]},{"_id":"62efda9f0cf252bc640928e2","purchaserUuid":"aea4c861dfa249eaadb625ad182606b9","amount":2,"originalLength":3600,"length":3600,"gameType":51,"dateActivated":1660064056778},{"_id":"62efda9f0cf252bc640928e1","purchaserUuid":"aea4c861dfa249eaadb625ad182606b9","amount":2,"originalLength":3600,"length":3600,"gameType":13,"dateActivated":1660064078089},{"_id":"62edbab70cf2beec62b0806d","purchaserUuid":"1f41bbe10cc74a1a809e3584b984aa76","amount":2,"originalLength":3600,"length":3600,"gameType":13,"dateActivated":1660065476262},{"_id":"629d23410cf225808cb415a6","purchaserUuid":"6a808cf704084cb89fbf14a8490f38c5","amount":2,"originalLength":3600,"length":3600,"gameType":51,"dateActivated":1660069878833},{"_id":"62f2a8b60cf2a3bd9b16e496","purchaserUuid":"59257cb6d13c45639bb37458e749b2f1","amount":2,"originalLength":3600,"length":3600,"gameType":13,"dateActivated":1660070238075},{"_id":"62f2a8b60cf2a3bd9b16e484","purchaserUuid":"59257cb6d13c45639bb37458e749b2f1","amount":2,"originalLength":3600,"length":3600,"gameType":51,"dateActivated":1660070290632},{"_id":"62f2a8b60cf2a3bd9b16e48e","purchaserUuid":"59257cb6d13c45639bb37458e749b2f1","amount":2.1,"originalLength":3600,"length":869,"gameType":56,"dateActivated":1660070299180,"stacked":["144abc37-63ec-41d7-9974-70c8d8969869"]},{"_id":"62edba780cf252bc640925da","purchaserUuid":"8cc67218649c4d819c9a9a49eae5dbd1","amount":2,"originalLength":3600,"length":3600,"gameType":13,"dateActivated":1660071587391},{"_id":"62edba7d0cf252bc640925ec","purchaserUuid":"8cc67218649c4d819c9a9a49eae5dbd1","amount":2,"originalLength":3600,"length":3600,"gameType":51,"dateActivated":1660071619326},{"_id":"62edba7d0cf252bc640925ef","purchaserUuid":"8cc67218649c4d819c9a9a49eae5dbd1","amount":2,"originalLength":3600,"length":3600,"gameType":56,"dateActivated":1660071626657},{"_id":"62f2b2160cf2a3bd9b16e4c8","purchaserUuid":"75e9897f42cf4963a3e9e9dd43a528b7","amount":2,"originalLength":3600,"length":3600,"gameType":51,"dateActivated":1660072528803},{"_id":"62f2b2160cf2a3bd9b16e4da","purchaserUuid":"75e9897f42cf4963a3e9e9dd43a528b7","amount":2,"originalLength":3600,"length":3600,"gameType":13,"dateActivated":1660072578888},{"_id":"62f2b2160cf2a3bd9b16e4d2","purchaserUuid":"75e9897f42cf4963a3e9e9dd43a528b7","amount":2,"originalLength":3600,"length":3600,"gameType":56,"dateActivated":1660072632946},{"_id":"62f2b4110cf252bc64092d34","purchaserUuid":"25fcb12901c444a08576da6538f460a6","amount":2,"originalLength":3600,"length":3600,"gameType":56,"dateActivated":1660073084318},{"_id":"62f2b5390cf252bc64092d41","purchaserUuid":"0d0f7d68cc02474d99cc66daf4c6c043","amount":2,"originalLength":3600,"length":3600,"gameType":56,"dateActivated":1660073333969},{"_id":"62ee934f0cf252bc64092701","purchaserUuid":"0e89ae03e2e149619627230918120b97","amount":2,"originalLength":3600,"length":3600,"gameType":13,"dateActivated":1660074039579},{"_id":"6069f3f30cf2c4d8b060de80","purchaserUuid":"b843581be4a24fa38d5518f99423ee48","amount":2,"originalLength":3600,"length":3600,"gameType":13,"dateActivated":1660074301498},{"_id":"61ba06f70cf26d6213ba7546","purchaserUuid":"2110994bc1164b74baf62d1203842301","amount":2,"originalLength":3600,"length":3600,"gameType":56,"dateActivated":1660075826717},{"_id":"61ba06f70cf26d6213ba753c","purchaserUuid":"2110994bc1164b74baf62d1203842301","amount":2,"originalLength":3600,"length":3600,"gameType":51,"dateActivated":1660075842317},{"_id":"62f2cbb50cf252bc64092d52","purchaserUuid":"59d6ad48f6774d20a92c78daf79ba487","amount":2,"originalLength":3600,"length":3600,"gameType":13,"dateActivated":1660079185774},{"_id":"62f2cbb50cf252bc64092d54","purchaserUuid":"59d6ad48f6774d20a92c78daf79ba487","amount":2,"originalLength":3600,"length":3600,"gameType":56,"dateActivated":1660079226020},{"_id":"62f040920cf252bc64092960","purchaserUuid":"ec6c6bc3959740189c31e9bc65041ad8","amount":2,"originalLength":3600,"length":3600,"gameType":51,"dateActivated":1660079229415},{"_id":"62f2cbb50cf252bc64092d51","purchaserUuid":"59d6ad48f6774d20a92c78daf79ba487","amount":2,"originalLength":3600,"length":3600,"gameType":51,"dateActivated":1660079245728},{"_id":"62f16f460cf252bc64092b3e","purchaserUuid":"beade9198d3d4ffb967e5e3ca46a1edf","amount":2,"originalLength":3600,"length":3600,"gameType":56,"dateActivated":1660079449607},{"_id":"62f16f460cf252bc64092b3b","purchaserUuid":"beade9198d3d4ffb967e5e3ca46a1edf","amount":2,"originalLength":3600,"length":3600,"gameType":51,"dateActivated":1660079457017},{"_id":"62efa4900cf2beec62b08d06","purchaserUuid":"45cad89005fd4fde871474e5b9d9e75e","amount":2,"originalLength":3600,"length":3600,"gameType":51,"dateActivated":1660084039165},{"_id":"62f2dfca0cf2a3bd9b16e5f7","purchaserUuid":"18b285d094cb4cb0bda89f6d63e414c5","amount":2,"originalLength":3600,"length":3600,"gameType":51,"dateActivated":1660084239365},{"_id":"62f108580cf2beec62b09559","purchaserUuid":"00be00279aff48a5b10939f3db06fb9b","amount":2,"originalLength":3600,"length":3600,"gameType":51,"dateActivated":1660085188124},{"_id":"62f108580cf2beec62b0955e","purchaserUuid":"00be00279aff48a5b10939f3db06fb9b","amount":2,"originalLength":3600,"length":3600,"gameType":56,"dateActivated":1660085193879},{"_id":"62f2e8760cf2a3bd9b16e660","purchaserUuid":"c6fca29203e048ffb94741d549730cce","amount":2,"originalLength":3600,"length":3600,"gameType":51,"dateActivated":1660086436605},{"_id":"62f2e8760cf2a3bd9b16e665","purchaserUuid":"c6fca29203e048ffb94741d549730cce","amount":2,"originalLength":3600,"length":3600,"gameType":56,"dateActivated":1660086514306},{"_id":"62f2e8760cf2a3bd9b16e669","purchaserUuid":"c6fca29203e048ffb94741d549730cce","amount":2,"originalLength":3600,"length":3600,"gameType":13,"dateActivated":1660086527599},{"_id":"62f2f7160cf252bc64092d81","purchaserUuid":"127cf4c1e56d42188fa7e08f96eafefb","amount":2,"originalLength":3600,"length":3600,"gameType":51,"dateActivated":1660090295610},{"_id":"62f2f7160cf252bc64092d82","purchaserUuid":"127cf4c1e56d42188fa7e08f96eafefb","amount":2,"originalLength":3600,"length":3600,"gameType":13,"dateActivated":1660090379394},{"_id":"62f2f7160cf252bc64092d84","purchaserUuid":"127cf4c1e56d42188fa7e08f96eafefb","amount":2,"originalLength":3600,"length":3600,"gameType":56,"dateActivated":1660090399894},{"_id":"62f2fa0a0cf2a3bd9b16e6d5","purchaserUuid":"17c47225f04746be9bf56685d79a0fa6","amount":2,"originalLength":3600,"length":3600,"gameType":51,"dateActivated":1660091017912},{"_id":"62f2fa0a0cf2a3bd9b16e6df","purchaserUuid":"17c47225f04746be9bf56685d79a0fa6","amount":2,"originalLength":3600,"length":3600,"gameType":56,"dateActivated":1660091029125},{"_id":"62f301c60cf2a3bd9b16e742","purchaserUuid":"011ae7816d53477c94f010634c581f5b","amount":2,"originalLength":3600,"length":3600,"gameType":13,"dateActivated":1660093045012},{"_id":"62f301c60cf2a3bd9b16e73a","purchaserUuid":"011ae7816d53477c94f010634c581f5b","amount":2,"originalLength":3600,"length":3600,"gameType":56,"dateActivated":1660093094353},{"_id":"62f301c60cf2a3bd9b16e730","purchaserUuid":"011ae7816d53477c94f010634c581f5b","amount":2,"originalLength":3600,"length":3600,"gameType":51,"dateActivated":1660093101952},{"_id":"62e356040cf252bc640916f4","purchaserUuid":"d9784cf822214b2d8f32cad8f3bb71b6","amount":2,"originalLength":3600,"length":3600,"gameType":51,"dateActivated":1660095905329},{"_id":"6131717144f4c19a4fd82e66","purchaserUuid":"f1a2c845d5094dbbb8477f863e2891e2","amount":2,"originalLength":3600,"length":3600,"gameType":51,"dateActivated":1660099308671},{"_id":"62d8bd6d0cf2beec62affae3","purchaserUuid":"fc033a20d56142d8ac056cbc2afb24a5","amount":2,"originalLength":3600,"length":3600,"gameType":13,"dateActivated":1660100386790},{"_id":"62f322d20cf2a3bd9b16e824","purchaserUuid":"b322c12e807345c3b1f3c4d25738893b","amount":2,"originalLength":3600,"length":3600,"gameType":13,"dateActivated":1660101379752},{"_id":"62f322d20cf2a3bd9b16e812","purchaserUuid":"b322c12e807345c3b1f3c4d25738893b","amount":2,"originalLength":3600,"length":3600,"gameType":51,"dateActivated":1660101427760},{"_id":"62f322d20cf2a3bd9b16e81c","purchaserUuid":"b322c12e807345c3b1f3c4d25738893b","amount":2,"originalLength":3600,"length":3600,"gameType":56,"dateActivated":1660101437470},{"_id":"62f324ec0cf252bc64092d9a","purchaserUuid":"1edad03b2d094147a597161b91d1ad78","amount":2,"originalLength":3600,"length":3600,"gameType":51,"dateActivated":1660101896894},{"_id":"62f2a8b60cf2a3bd9b16e497","purchaserUuid":"59257cb6d13c45639bb37458e749b2f1","amount":2,"originalLength":3600,"length":3600,"gameType":13,"dateActivated":1660110691818},{"_id":"62f2a8b60cf2a3bd9b16e485","purchaserUuid":"59257cb6d13c45639bb37458e749b2f1","amount":2,"originalLength":3600,"length":3600,"gameType":51,"dateActivated":1660110729579},{"_id":"62f2a8b60cf2a3bd9b16e48f","purchaserUuid":"59257cb6d13c45639bb37458e749b2f1","amount":2,"originalLength":3600,"length":3600,"gameType":56,"dateActivated":1660110736219},{"_id":"62f301120cf2a3bd9b16e72e","purchaserUuid":"f55954ae39cc41899aaa3e11627c3def","amount":2,"originalLength":3600,"length":3600,"gameType":13,"dateActivated":1660113002983},{"_id":"62e60fd60cf2beec62b0502b","purchaserUuid":"5d6eab327cb84e87a41556f09fba09b3","amount":2,"originalLength":3600,"length":3600,"gameType":56,"dateActivated":1660113492323},{"_id":"61b4069b44f4bf98fd491195","purchaserUuid":"96de366e5bfc4639b6f12b93170feceb","amount":2,"originalLength":3600,"length":3600,"gameType":13,"dateActivated":1660116789243},{"_id":"61b4069b44f4bf98fd491194","purchaserUuid":"96de366e5bfc4639b6f12b93170feceb","amount":2,"originalLength":3600,"length":3600,"gameType":51,"dateActivated":1660116812182},{"_id":"62f1fcc50cf252bc64092be9","purchaserUuid":"8f91808b66054aaa84ed04b231ce465f","amount":2,"originalLength":3600,"length":3600,"gameType":51,"dateActivated":1660117643888},{"_id":"62f368e60cf2a3bd9b16e925","purchaserUuid":"52b0967334604dc4a8fe37062588d33a","amount":2,"originalLength":3600,"length":3600,"gameType":51,"dateActivated":1660120600980},{"_id":"600fa49e44f4fda7007b4235","purchaserUuid":"a5f69a3c19cd48bfa4f3ebd17020306d","amount":2,"originalLength":3600,"length":3600,"gameType":13,"dateActivated":1660121350330},{"_id":"62f38aef0cf252bc64092dee","purchaserUuid":"64ef76d1a8b64ba39a9faa9ba0de7d30","amount":2,"originalLength":3600,"length":3600,"gameType":13,"dateActivated":1660127999445},{"_id":"62f38aef0cf252bc64092df0","purchaserUuid":"64ef76d1a8b64ba39a9faa9ba0de7d30","amount":2,"originalLength":3600,"length":3600,"gameType":56,"dateActivated":1660128042309},{"_id":"62efc6aa0cf252bc64092863","purchaserUuid":"7ccb3ffad6a34f00bf092eda457762f3","amount":2,"originalLength":3600,"length":3600,"gameType":56,"dateActivated":1660131668307},{"_id":"62efc6aa0cf252bc64092860","purchaserUuid":"7ccb3ffad6a34f00bf092eda457762f3","amount":2,"originalLength":3600,"length":3600,"gameType":51,"dateActivated":1660131677218},{"_id":"62e6862f0cf2beec62b0528c","purchaserUuid":"00be00279aff48a5b10939f3db06fb9b","amount":2,"originalLength":3600,"length":3600,"gameType":56,"dateActivated":1660132999269},{"_id":"62e6862f0cf2beec62b05282","purchaserUuid":"00be00279aff48a5b10939f3db06fb9b","amount":2,"originalLength":3600,"length":3600,"gameType":51,"dateActivated":1660133008040},{"_id":"62f036d00cf2beec62b09144","purchaserUuid":"9e7fb26ed2a84e14b508a4be92d432b3","amount":2,"originalLength":3600,"length":3600,"gameType":51,"dateActivated":1660135316027},{"_id":"62f036d10cf2beec62b09167","purchaserUuid":"9e7fb26ed2a84e14b508a4be92d432b3","amount":2,"originalLength":3600,"length":3600,"gameType":13,"dateActivated":1660135361841},{"_id":"62f036d00cf2beec62b09157","purchaserUuid":"9e7fb26ed2a84e14b508a4be92d432b3","amount":2,"originalLength":3600,"length":3600,"gameType":56,"dateActivated":1660135455728},{"_id":"62f16f520cf252bc64092b40","purchaserUuid":"beade9198d3d4ffb967e5e3ca46a1edf","amount":2,"originalLength":3600,"length":3600,"gameType":13,"dateActivated":1660141588612},{"_id":"62f3a9250cf252bc64092e47","purchaserUuid":"24a79bcc81a6493087e5a9ffdd2ed6ba","amount":2,"originalLength":3600,"length":3600,"gameType":56,"dateActivated":1660141610392},{"_id":"62f3c1360cf252bc64092e70","purchaserUuid":"585837515da746fa834b1e82c75295fb","amount":2,"originalLength":3600,"length":3600,"gameType":51,"dateActivated":1660142027110},{"_id":"62f3c1360cf252bc64092e73","purchaserUuid":"585837515da746fa834b1e82c75295fb","amount":2,"originalLength":3600,"length":3600,"gameType":56,"dateActivated":1660142040066},{"_id":"62f3b8d20cf2a3bd9b16ea4b","purchaserUuid":"96875f56ce054e318a6b224d5f3a8ad2","amount":2,"originalLength":3600,"length":3600,"gameType":56,"dateActivated":1660142695566},{"_id":"62f3d0ba0cf2a3bd9b16eaba","purchaserUuid":"7c16ec4ee7ef40518ff96020880aecbb","amount":2,"originalLength":3600,"length":3600,"gameType":56,"dateActivated":1660145911403},{"_id":"62b4e0d10cf252bc6408c35f","purchaserUuid":"3078527cadf74d88a735e4415c19180d","amount":2,"originalLength":3600,"length":3600,"gameType":56,"dateActivated":1660148680615},{"_id":"62f2c3f40cf252bc64092d49","purchaserUuid":"74ad2a288cb8487eb962801c489f5269","amount":2,"originalLength":3600,"length":3600,"gameType":51,"dateActivated":1660151631346},{"_id":"62f2fa0a0cf2a3bd9b16e6e8","purchaserUuid":"17c47225f04746be9bf56685d79a0fa6","amount":2,"originalLength":3600,"length":3600,"gameType":13,"dateActivated":1660156116368},{"_id":"62f2fa0a0cf2a3bd9b16e6d6","purchaserUuid":"17c47225f04746be9bf56685d79a0fa6","amount":2,"originalLength":3600,"length":3600,"gameType":51,"dateActivated":1660156158681},{"_id":"62e805270cf2beec62b05cc8","purchaserUuid":"0480da6c47ba4dffa790794d3089e2b4","amount":2,"originalLength":3600,"length":3600,"gameType":13,"dateActivated":1660157403766},{"_id":"62e805270cf2beec62b05cb6","purchaserUuid":"0480da6c47ba4dffa790794d3089e2b4","amount":2,"originalLength":3600,"length":3600,"gameType":51,"dateActivated":1660157476206},{"_id":"62e805270cf2beec62b05cc0","purchaserUuid":"0480da6c47ba4dffa790794d3089e2b4","amount":2,"originalLength":3600,"length":3600,"gameType":56,"dateActivated":1660157484299},{"_id":"62ee934f0cf252bc6409270b","purchaserUuid":"0e89ae03e2e149619627230918120b97","amount":2,"originalLength":3600,"length":3600,"gameType":13,"dateActivated":1660159335372},{"_id":"62ee934f0cf252bc6409270c","purchaserUuid":"0e89ae03e2e149619627230918120b97","amount":2,"originalLength":3600,"length":3600,"gameType":51,"dateActivated":1660159352921},{"_id":"62cff5c40cf2beec62afc0b0","purchaserUuid":"9534061962ac44d39674def29910a7af","amount":2,"originalLength":3600,"length":3600,"gameType":13,"dateActivated":1660162267817},{"_id":"62cff5c40cf2beec62afc08c","purchaserUuid":"9534061962ac44d39674def29910a7af","amount":2,"originalLength":3600,"length":3600,"gameType":51,"dateActivated":1660162280336},{"_id":"62cff5c40cf2beec62afc0a0","purchaserUuid":"9534061962ac44d39674def29910a7af","amount":2,"originalLength":3600,"length":3600,"gameType":56,"dateActivated":1660162301197},{"_id":"62bef3560cf252bc6408dea1","purchaserUuid":"99fe72e4009e4d36a9746f263ffc5e50","amount":2,"originalLength":3600,"length":3600,"gameType":56,"dateActivated":1660162846577},{"_id":"62f417c60cf252bc64092ecf","purchaserUuid":"5171cabc713a467eac069515b60e773f","amount":2,"originalLength":3600,"length":3600,"gameType":51,"dateActivated":1660164337264},{"_id":"62f417c60cf252bc64092ed0","purchaserUuid":"5171cabc713a467eac069515b60e773f","amount":2,"originalLength":3600,"length":3600,"gameType":13,"dateActivated":1660165154364},{"_id":"62f428510cf252bc64092eeb","purchaserUuid":"cf514eb475124933adc1b1ccb11b375b","amount":2,"originalLength":3600,"length":3600,"gameType":13,"dateActivated":1660168408355},{"_id":"62f428510cf252bc64092eec","purchaserUuid":"cf514eb475124933adc1b1ccb11b375b","amount":2,"originalLength":3600,"length":3600,"gameType":51,"dateActivated":1660168470737},{"_id":"62f428510cf252bc64092ee9","purchaserUuid":"cf514eb475124933adc1b1ccb11b375b","amount":2,"originalLength":3600,"length":3600,"gameType":56,"dateActivated":1660168484238},{"_id":"62bc643a0cf2beec62af2e7a","purchaserUuid":"c250b780444649f7b16e983cdfc3a69f","amount":2.1,"originalLength":3600,"length":2699,"gameType":14,"dateActivated":1660170440420,"stacked":["a0a28e11-2648-4b5d-8175-e250be753704"]},{"_id":"62e522a30cf2beec62b0492b","purchaserUuid":"b29172f9554f4779b8d54ca600f17d9a","amount":2,"originalLength":3600,"length":3600,"gameType":13,"dateActivated":1660171072532},{"_id":"62e522a30cf2beec62b04924","purchaserUuid":"b29172f9554f4779b8d54ca600f17d9a","amount":2,"originalLength":3600,"length":3600,"gameType":56,"dateActivated":1660171110088},{"_id":"62bfbe170cf252bc6408dfd0","purchaserUuid":"05eef8392b294a9e99e1867571fef041","amount":2,"originalLength":3600,"length":3600,"gameType":13,"dateActivated":1660171378503},{"_id":"62bfbe170cf252bc6408dfd2","purchaserUuid":"05eef8392b294a9e99e1867571fef041","amount":2,"originalLength":3600,"length":3600,"gameType":56,"dateActivated":1660171391367},{"_id":"613e205744f46f62e54fe45a","purchaserUuid":"0e4111899eb5424ab44d0b16dbfcf3dd","amount":2,"originalLength":3600,"length":3600,"gameType":13,"dateActivated":1660173263192},{"_id":"62a91ffc0cf225808cb41c95","purchaserUuid":"b843581be4a24fa38d5518f99423ee48","amount":2,"originalLength":3600,"length":3600,"gameType":56,"dateActivated":1660176817423},{"_id":"62f453fa0cf2a3bd9b16ee05","purchaserUuid":"62a6dd205b584edeb95139a5e7b7ed15","amount":2.1,"originalLength":3600,"length":3299,"gameType":20,"dateActivated":1660179476795,"stacked":["02220b27-c180-4267-8913-5f76234728ce"]},{"_id":"619a8a530cf2e2db682b2ffe","purchaserUuid":"8601adfe0be543adaa85bb4805cd79c1","amount":2,"originalLength":3600,"length":3600,"gameType":51,"dateActivated":1660180204840},{"_id":"619a8a530cf2e2db682b2ffa","purchaserUuid":"8601adfe0be543adaa85bb4805cd79c1","amount":2,"originalLength":3600,"length":3600,"gameType":56,"dateActivated":1660180231077},{"_id":"619a8a530cf2e2db682b2ffb","purchaserUuid":"8601adfe0be543adaa85bb4805cd79c1","amount":2,"originalLength":3600,"length":3600,"gameType":20,"dateActivated":1660180241512},{"_id":"619a8a530cf2e2db682b2ffd","purchaserUuid":"8601adfe0be543adaa85bb4805cd79c1","amount":2,"originalLength":3600,"length":3600,"gameType":13,"dateActivated":1660180284199},{"_id":"62f322d20cf2a3bd9b16e81d","purchaserUuid":"b322c12e807345c3b1f3c4d25738893b","amount":2,"originalLength":3600,"length":3600,"gameType":14,"dateActivated":1660180960768},{"_id":"62f322d20cf2a3bd9b16e81f","purchaserUuid":"b322c12e807345c3b1f3c4d25738893b","amount":2,"originalLength":3600,"length":3600,"gameType":20,"dateActivated":1660180969993},{"_id":"61571c9344f46f62e54ffc66","purchaserUuid":"dff78ea1e41b40ea811a183a42547db4","amount":2,"originalLength":3600,"length":3600,"gameType":56,"dateActivated":1660187243376},{"_id":"62d8bd6d0cf2beec62affadf","purchaserUuid":"fc033a20d56142d8ac056cbc2afb24a5","amount":2,"originalLength":3600,"length":3600,"gameType":20,"dateActivated":1660188436291},{"_id":"62d8bd6d0cf2beec62affad1","purchaserUuid":"fc033a20d56142d8ac056cbc2afb24a5","amount":2,"originalLength":3600,"length":3600,"gameType":51,"dateActivated":1660188458255},{"_id":"62d8bd6d0cf2beec62affadb","purchaserUuid":"fc033a20d56142d8ac056cbc2afb24a5","amount":2,"originalLength":3600,"length":3600,"gameType":56,"dateActivated":1660188465756},{"_id":"5d2817e944f482d28f99facb","purchaserUuid":"da0091e389e44781b0c3719a8c4c84d9","amount":2,"originalLength":3600,"length":3600,"gameType":13,"dateActivated":1660189335445},{"_id":"62df51e20cf2beec62b02773","purchaserUuid":"357804eb75214b829be1d7ee5cda7cce","amount":2,"originalLength":3600,"length":3600,"gameType":20,"dateActivated":1660190247322},{"_id":"62df51e20cf2beec62b02767","purchaserUuid":"357804eb75214b829be1d7ee5cda7cce","amount":2.3,"originalLength":3600,"length":1690,"gameType":6,"dateActivated":1660190254824,"stacked":["02220b27-c180-4267-8913-5f76234728ce","144abc37-63ec-41d7-9974-70c8d8969869","d8d63a97-d299-466d-93b2-cfce16791529"]},{"_id":"62df51e20cf2beec62b0276f","purchaserUuid":"357804eb75214b829be1d7ee5cda7cce","amount":2,"originalLength":3600,"length":3600,"gameType":56,"dateActivated":1660190262716},{"_id":"62f3c05f0cf252bc64092e64","purchaserUuid":"f98746dfc1324ab898ec39312546de94","amount":2.2,"originalLength":3600,"length":33,"gameType":24,"dateActivated":1660190538629,"stacked":["78f29426-21c4-4b71-b954-5669d00fd094","144abc37-63ec-41d7-9974-70c8d8969869"]},{"_id":"62f3c05f0cf252bc64092e5f","purchaserUuid":"f98746dfc1324ab898ec39312546de94","amount":2,"originalLength":3600,"length":3600,"gameType":51,"dateActivated":1660190546741},{"_id":"62f3c05f0cf252bc64092e5c","purchaserUuid":"f98746dfc1324ab898ec39312546de94","amount":2,"originalLength":3600,"length":3600,"gameType":56,"dateActivated":1660190554331},{"_id":"62f036d00cf2beec62b09145","purchaserUuid":"9e7fb26ed2a84e14b508a4be92d432b3","amount":2,"originalLength":3600,"length":3600,"gameType":51,"dateActivated":1660190847470},{"_id":"62f036d10cf2beec62b0915f","purchaserUuid":"9e7fb26ed2a84e14b508a4be92d432b3","amount":2,"originalLength":3600,"length":3600,"gameType":20,"dateActivated":1660190865679},{"_id":"61b4069b44f4bf98fd491197","purchaserUuid":"96de366e5bfc4639b6f12b93170feceb","amount":2,"originalLength":3600,"length":3600,"gameType":56,"dateActivated":1660191574737},{"_id":"62f4850e0cf252bc64092f74","purchaserUuid":"57e8b6825d154f02b2096462248e8a02","amount":2,"originalLength":3600,"length":3600,"gameType":20,"dateActivated":1660192025502},{"_id":"62b3bec70cf225808cb4231c","purchaserUuid":"6bd5955e17af484b91e37bcd9f55673e","amount":2,"originalLength":3600,"length":3600,"gameType":13,"dateActivated":1660192075075},{"_id":"62f48d400cf252bc64092f76","purchaserUuid":"03d2b733d24040399d86c1dafa5bc93c","amount":2,"originalLength":3600,"length":3600,"gameType":13,"dateActivated":1660194213009},{"_id":"62f48d400cf252bc64092f77","purchaserUuid":"03d2b733d24040399d86c1dafa5bc93c","amount":2,"originalLength":3600,"length":3600,"gameType":14,"dateActivated":1660194314460},{"_id":"62ea51330cf2beec62b06b25","purchaserUuid":"19bb2cdde0fd471ab00f4e93c416aa9a","amount":2,"originalLength":3600,"length":3600,"gameType":14,"dateActivated":1660194651841},{"_id":"62ea51330cf2beec62b06b29","purchaserUuid":"19bb2cdde0fd471ab00f4e93c416aa9a","amount":2,"originalLength":3600,"length":3600,"gameType":20,"dateActivated":1660194671144},{"_id":"62ea51330cf2beec62b06b39","purchaserUuid":"19bb2cdde0fd471ab00f4e93c416aa9a","amount":2,"originalLength":3600,"length":3600,"gameType":24,"dateActivated":1660194693364},{"_id":"62ea51330cf2beec62b06b32","purchaserUuid":"19bb2cdde0fd471ab00f4e93c416aa9a","amount":2,"originalLength":3600,"length":3600,"gameType":51,"dateActivated":1660194700107},{"_id":"62ea51330cf2beec62b06b20","purchaserUuid":"19bb2cdde0fd471ab00f4e93c416aa9a","amount":2,"originalLength":3600,"length":3600,"gameType":56,"dateActivated":1660194710673},{"_id":"62ea51330cf2beec62b06b31","purchaserUuid":"19bb2cdde0fd471ab00f4e93c416aa9a","amount":2,"originalLength":3600,"length":3600,"gameType":13,"dateActivated":1660194725879},{"_id":"62ea51330cf2beec62b06b11","purchaserUuid":"19bb2cdde0fd471ab00f4e93c416aa9a","amount":2,"originalLength":3600,"length":3600,"gameType":6,"dateActivated":1660194732232},{"_id":"62c5251b0cf252bc6408e7d4","purchaserUuid":"a218bf354c844b1b90dc859bb063dd2f","amount":2,"originalLength":3600,"length":3600,"gameType":13,"dateActivated":1660196139579},{"_id":"62e31ff40cf252bc64091694","purchaserUuid":"7d44983d771a4164a048c3a8f1109e60","amount":2,"originalLength":3600,"length":3600,"gameType":56,"dateActivated":1660197560753},{"_id":"62f0d3600cf2beec62b0948b","purchaserUuid":"5a2efc5207964bb3b883c01521d65a8a","amount":2,"originalLength":3600,"length":3600,"gameType":24,"dateActivated":1660197749179},{"_id":"62f4aa230cf252bc64092fa4","purchaserUuid":"732f6c59f74f4e9283f2278d78c866c5","amount":2,"originalLength":3600,"length":3600,"gameType":20,"dateActivated":1660201599852},{"_id":"62f2b4110cf252bc64092d2b","purchaserUuid":"25fcb12901c444a08576da6538f460a6","amount":2,"originalLength":3600,"length":2802,"gameType":5,"dateActivated":1660201881949},{"_id":"62f2b40a0cf252bc64092d26","purchaserUuid":"25fcb12901c444a08576da6538f460a6","amount":2,"originalLength":3600,"length":3600,"gameType":6,"dateActivated":1660201888360},{"_id":"62f2b4110cf252bc64092d36","purchaserUuid":"25fcb12901c444a08576da6538f460a6","amount":2,"originalLength":3600,"length":3600,"gameType":13,"dateActivated":1660201895011},{"_id":"62f2b4110cf252bc64092d2f","purchaserUuid":"25fcb12901c444a08576da6538f460a6","amount":2,"originalLength":3600,"length":3600,"gameType":14,"dateActivated":1660201902582},{"_id":"62f2b40a0cf252bc64092d29","purchaserUuid":"25fcb12901c444a08576da6538f460a6","amount":2,"originalLength":3600,"length":1860,"gameType":21,"dateActivated":1660201908830},{"_id":"62f2b4110cf252bc64092d38","purchaserUuid":"25fcb12901c444a08576da6538f460a6","amount":2,"originalLength":3600,"length":3600,"gameType":20,"dateActivated":1660201915916},{"_id":"62f2b40a0cf252bc64092d28","purchaserUuid":"25fcb12901c444a08576da6538f460a6","amount":2,"originalLength":3600,"length":3600,"gameType":24,"dateActivated":1660201929355},{"_id":"62f435460cf2a3bd9b16ed27","purchaserUuid":"9484a4b3df51418386e4b4f38558fcb4","amount":2,"originalLength":3600,"length":1876,"gameType":23,"dateActivated":1660202556074,"stacked":[]},{"_id":"62f1d5540cf252bc64092baa","purchaserUuid":"78f2942621c44b71b9545669d00fd094","amount":2,"originalLength":3600,"length":3600,"gameType":5,"dateActivated":1660202885022},{"_id":"62f1d5480cf252bc64092b9b","purchaserUuid":"78f2942621c44b71b9545669d00fd094","amount":2,"originalLength":3600,"length":3600,"gameType":6,"dateActivated":1660202891373},{"_id":"62f1d5480cf252bc64092b9a","purchaserUuid":"78f2942621c44b71b9545669d00fd094","amount":2,"originalLength":3600,"length":3600,"gameType":14,"dateActivated":1660202910378},{"_id":"62f452560cf2a3bd9b16edf9","purchaserUuid":"a768a431c1f0426ebab39780fbf9b464","amount":2,"originalLength":3600,"length":3600,"gameType":20,"dateActivated":1660203320037},{"_id":"62f27ce20cf2a3bd9b16e37a","purchaserUuid":"144abc3763ec41d7997470c8d8969869","amount":2,"originalLength":3600,"length":3600,"gameType":21,"dateActivated":1660205075105},{"_id":"62f27ce20cf2a3bd9b16e385","purchaserUuid":"144abc3763ec41d7997470c8d8969869","amount":2,"originalLength":3600,"length":3600,"gameType":23,"dateActivated":1660205095128},{"_id":"62f27d960cf2a3bd9b16e3af","purchaserUuid":"42951d945c3f4be29df42e36970b0741","amount":2,"originalLength":3600,"length":3600,"gameType":23,"dateActivated":1660207299341},{"_id":"62f27d960cf2a3bd9b16e3b2","purchaserUuid":"42951d945c3f4be29df42e36970b0741","amount":2,"originalLength":3600,"length":3600,"gameType":20,"dateActivated":1660207318757},{"_id":"62bdc0fa0cf2beec62af36c6","purchaserUuid":"d3326274d0ed4f8cbbd27e469ddd9547","amount":2,"originalLength":3600,"length":3600,"gameType":14,"dateActivated":1660207588688},{"_id":"62eb9f540cf252bc640922db","purchaserUuid":"4c0b8240e681417d920b62724b4c7f03","amount":2,"originalLength":3600,"length":3600,"gameType":56,"dateActivated":1660207740000},{"_id":"62f4c3290cf252bc64092fd3","purchaserUuid":"a0a28e1126484b5d8175e250be753704","amount":2,"originalLength":3600,"length":3600,"gameType":56,"dateActivated":1660207953008,"stacked":true}],"boosterState":{"decrementing":true}}