{"success":true,"games":{"MAIN_LOBBY":{"players":601},"TOURNAMENT_LOBBY":{"players":10},"SMP":{"players":1131},"LEGACY":{"players":96,"modes":{"PAINTBALL":1,"VAMPIREZ":44,"GINGERBREAD":9,"ARENA":1,"QUAKECRAFT":2,"WALLS":16}},"TNTGAMES":{"players":337,"modes":{"TNTAG":165,"TNTRUN":94,"BOWSPLEEF":7,"CAPTURE":23}},"SURVIVAL_GAMES":{"players":133,"modes":{"solo_normal":59,"teams_normal":39}},"BUILD_BATTLE":{"players":608,"modes":{"BUILD_BATTLE_SOLO_NORMAL_LATEST":158,"BUILD_BATTLE_GUESS_THE_BUILD":82,"BUILD_BATTLE_TEAMS_NORMAL":176,"BUILD_BATTLE_SOLO_NORMAL":93,"BUILD_BATTLE_SOLO_PRO":25}},"WOOL_GAMES":{"players":187,"modes":{"wool_wars_two_four":149}},"BEDWARS":{"players":7829,"modes":{"BEDWARS_TWO_FOUR":471,"BEDWARS_FOUR_THREE":837,"BEDWARS_EIGHT_ONE":984,"BEDWARS_EIGHT_TWO_RUSH":3,"BEDWARS_FOUR_FOUR_ARMED":339,"BEDWARS_EIGHT_TWO_ARMED":223,"BEDWARS_EIGHT_TWO":2015,"BEDWARS_FOUR_FOUR":1722,"BEDWARS_EIGHT_TWO_LUCKY":6,"BEDWARS_PRACTICE":140}},"PROTOTYPE":{"players":251,"modes":{"PIXEL_PARTY":45}},"DUELS":{"players":1501,"modes":{"DUELS_BOWSPLEEF_DUEL":23,"DUELS_BOW_DUEL":16,"DUELS_UHC_FOUR":22,"DUELS_MW_DUEL":12,"DUELS_UHC_MEETUP":2,"DUELS_SW_DOUBLES":28,"DUELS_UHC_DOUBLES":42,"DUELS_BRIDGE_FOUR":12,"DUELS_SUMO_DUEL":78,"DUELS_BRIDGE_THREES":26,"DUELS_OP_DUEL":36,"DUELS_DUEL_ARENA":4,"DUELS_COMBO_DUEL":26,"DUELS_BRIDGE_2V2V2V2":1,"DUELS_BRIDGE_DOUBLES":79,"DUELS_BOXING_DUEL":12,"DUELS_BRIDGE_3V3V3V3":1,"DUELS_UHC_DUEL":94,"DUELS_OP_DOUBLES":12,"DUELS_PARKOUR_EIGHT":83,"DUELS_BLITZ_DUEL":54,"DUELS_POTION_DUEL":3,"DUELS_CLASSIC_DUEL":162,"DUELS_BRIDGE_DUEL":296,"DUELS_SW_DUEL":108}},"MURDER_MYSTERY":{"players":633,"modes":{"MURDER_DOUBLE_UP":152,"MURDER_INFECTION":74,"MURDER_ASSASSINS":34,"MURDER_CLASSIC":286}},"SPEED_UHC":{"players":10,"modes":{"solo_normal":10}},"UHC":{"players":120,"modes":{"TEAMS":2,"SOLO":87}},"SUPER_SMASH":{"players":29,"modes":{"1v1_normal":2,"2v2_normal":6}},"MCGO":{"players":64,"modes":{"normal":46,"gungame":2,"deathmatch":6}},"REPLAY":{"players":54,"modes":{"BASE":54}},"SKYWARS":{"players":1463,"modes":{"ranked_normal":66,"solo_insane_slime":2,"solo_normal":469,"teams_insane":101,"solo_insane_hunters_vs_beasts":4,"solo_insane":389,"teams_normal":148,"mega_normal":1}},"PIT":{"players":168,"modes":{"PIT":168}},"SKYBLOCK":{"players":19278,"modes":{"instanced":23,"dungeon_hub":639,"farming_1":295,"mining_2":647,"crimson_isle":437,"mining_3":1440,"combat_3":820,"crystal_hollows":1313,"dynamic":7210,"combat_1":263,"foraging_1":359,"hub":4261,"dungeon":1423,"mining_1":150}},"WALLS3":{"players":15,"modes":{"standard":2}},"BATTLEGROUND":{"players":52,"modes":{"domination":1,"team_deathmatch":40}},"ARCADE":{"players":979,"modes":{"PARTY":179,"HOLE_IN_THE_WALL":3,"DEFENDER":37,"SIMON_SAYS":46,"ZOMBIES_BAD_BLOOD":19,"HIDE_AND_SEEK_PARTY_POOPER":24,"DAYONE":60,"DRAW_THEIR_THING":10,"ZOMBIES_ALIEN_ARCADIUM":93,"SOCCER":13,"PVP_CTW":99,"ENDER":11,"ZOMBIES_DEAD_END":171,"HIDE_AND_SEEK_PROP_HUNT":52,"FARM_HUNT":49}},"HOUSING":{"players":1370},"LIMBO":{"players":246},"IDLE":{"players":4662},"QUEUE":{"players":0}},"playerCount":41753}