{"success":true,"games":{"MAIN_LOBBY":{"players":315},"TOURNAMENT_LOBBY":{"players":0},"SMP":{"players":641},"BEDWARS":{"players":18156,"modes":{"BEDWARS_FOUR_FOUR_VOIDLESS":3,"BEDWARS_TWO_FOUR":675,"BEDWARS_FOUR_THREE":2258,"BEDWARS_FOUR_FOUR_LUCKY":9,"BEDWARS_EIGHT_ONE":2539,"BEDWARS_FOUR_FOUR_ARMED":651,"BEDWARS_EIGHT_TWO_ARMED":362,"BEDWARS_FOUR_FOUR":3748,"BEDWARS_EIGHT_TWO":5081,"BEDWARS_EIGHT_TWO_LUCKY":11,"BEDWARS_PRACTICE":434,"BEDWARS_EIGHT_TWO_ULTIMATE":13}},"WALLS3":{"players":150,"modes":{"standard":136}},"TNTGAMES":{"players":605,"modes":{"TNTAG":268,"PVPRUN":13,"TNTRUN":156,"BOWSPLEEF":51,"CAPTURE":24}},"LEGACY":{"players":185,"modes":{"WALLS":34,"ARENA":12,"QUAKECRAFT":9,"PAINTBALL":23,"VAMPIREZ":61,"GINGERBREAD":6}},"ARCADE":{"players":1550,"modes":{"PARTY":308,"HOLE_IN_THE_WALL":24,"DEFENDER":13,"MINI_WALLS":53,"SIMON_SAYS":39,"ZOMBIES_BAD_BLOOD":41,"HIDE_AND_SEEK_PARTY_POOPER":28,"DAYONE":101,"DRAW_THEIR_THING":37,"ZOMBIES_ALIEN_ARCADIUM":136,"SOCCER":15,"PVP_CTW":161,"STARWARS":13,"DRAGONWARS2":2,"ZOMBIES_DEAD_END":249,"HIDE_AND_SEEK_PROP_HUNT":67,"FARM_HUNT":60}},"SURVIVAL_GAMES":{"players":133,"modes":{"solo_normal":58,"teams_normal":58}},"PIT":{"players":545,"modes":{"PIT":545}},"SKYWARS":{"players":3032,"modes":{"ranked_normal":115,"solo_insane_tnt_madness":47,"solo_insane_lucky":135,"teams_insane_lucky":83,"solo_insane_rush":3,"teams_insane":213,"solo_normal":871,"solo_insane_hunters_vs_beasts":9,"solo_insane":749,"teams_normal":280,"mega_normal":8}},"REPLAY":{"players":74,"modes":{"BASE":74}},"SUPER_SMASH":{"players":42,"modes":{"1v1_normal":4,"solo_normal":8,"2v2_normal":5}},"PROTOTYPE":{"players":351,"modes":{"TOWERWARS_SOLO":33,"TOWERWARS_TEAM_OF_TWO":14}},"MURDER_MYSTERY":{"players":941,"modes":{"MURDER_DOUBLE_UP":267,"MURDER_INFECTION":79,"MURDER_ASSASSINS":62,"MURDER_CLASSIC":400}},"MCGO":{"players":103,"modes":{"normal":62,"deathmatch":27}},"BUILD_BATTLE":{"players":853,"modes":{"BUILD_BATTLE_SOLO_NORMAL_LATEST":194,"BUILD_BATTLE_GUESS_THE_BUILD":88,"BUILD_BATTLE_TEAMS_NORMAL":268,"BUILD_BATTLE_SOLO_PRO":62,"BUILD_BATTLE_SOLO_NORMAL":144}},"UHC":{"players":461,"modes":{"TEAMS":288,"SOLO":120}},"HOUSING":{"players":1966},"SKYBLOCK":{"players":26213,"modes":{"dungeon_hub":952,"farming_1":340,"mining_2":685,"mining_3":1736,"combat_3":1115,"crystal_hollows":1823,"dynamic":11013,"combat_1":281,"foraging_1":395,"hub":5190,"combat_2":163,"dungeon":2367,"mining_1":155}},"SPEED_UHC":{"players":56,"modes":{"team_normal":24,"solo_normal":32}},"DUELS":{"players":3184,"modes":{"DUELS_BOWSPLEEF_DUEL":25,"DUELS_BOW_DUEL":13,"DUELS_MW_DUEL":28,"DUELS_UHC_FOUR":38,"DUELS_UHC_MEETUP":34,"DUELS_BRIDGE_DOUBLES":173,"DUELS_SW_DOUBLES":61,"DUELS_UHC_DOUBLES":63,"DUELS_BRIDGE_FOUR":42,"DUELS_BRIDGE_3V3V3V3":18,"DUELS_UHC_DUEL":341,"DUELS_SUMO_DUEL":196,"DUELS_OP_DOUBLES":21,"DUELS_OP_DUEL":57,"DUELS_BLITZ_DUEL":32,"DUELS_CLASSIC_DUEL":250,"DUELS_POTION_DUEL":23,"DUELS_COMBO_DUEL":14,"DUELS_BRIDGE_DUEL":887,"DUELS_SW_DUEL":180}},"BATTLEGROUND":{"players":88,"modes":{"ctf_mini":47,"domination":3,"team_deathmatch":3}},"LIMBO":{"players":215},"IDLE":{"players":7513},"QUEUE":{"players":0}},"playerCount":67247}