{"success":true,"games":{"MAIN_LOBBY":{"players":214},"TOURNAMENT_LOBBY":{"players":1},"SMP":{"players":852},"SKYWARS":{"players":1635,"modes":{"ranked_normal":41,"solo_insane_tnt_madness":1,"solo_insane_lucky":80,"teams_insane_lucky":3,"teams_insane":121,"solo_normal":513,"solo_insane":387,"teams_normal":170}},"LEGACY":{"players":86,"modes":{"PAINTBALL":15,"WALLS":19,"QUAKECRAFT":4,"ARENA":0,"VAMPIREZ":26,"GINGERBREAD":6}},"UHC":{"players":130,"modes":{"SOLO":100}},"BATTLEGROUND":{"players":49,"modes":{"ctf_mini":25}},"DUELS":{"players":2205,"modes":{"DUELS_BOWSPLEEF_DUEL":28,"DUELS_BOW_DUEL":27,"DUELS_UHC_FOUR":20,"DUELS_MW_DUEL":10,"DUELS_SW_DOUBLES":49,"DUELS_UHC_DOUBLES":31,"DUELS_BRIDGE_FOUR":11,"DUELS_SUMO_DUEL":118,"DUELS_BRIDGE_THREES":35,"DUELS_OP_DUEL":44,"DUELS_MW_DOUBLES":4,"DUELS_DUEL_ARENA":21,"DUELS_COMBO_DUEL":26,"DUELS_BRIDGE_2V2V2V2":1,"DUELS_BRIDGE_DOUBLES":149,"DUELS_BOXING_DUEL":16,"DUELS_UHC_DUEL":165,"DUELS_OP_DOUBLES":10,"DUELS_PARKOUR_EIGHT":152,"DUELS_CAPTURE_THREES":13,"DUELS_BLITZ_DUEL":44,"DUELS_POTION_DUEL":10,"DUELS_CLASSIC_DUEL":156,"DUELS_BRIDGE_DUEL":493,"DUELS_SW_DUEL":104}},"SKYBLOCK":{"players":17108,"modes":{"dungeon_hub":596,"farming_1":205,"mining_2":496,"mining_3":1086,"combat_3":997,"crystal_hollows":1010,"dynamic":6577,"combat_1":226,"foraging_1":358,"hub":3885,"combat_2":103,"dungeon":1464,"mining_1":110}},"ARCADE":{"players":1021,"modes":{"PARTY":221,"HOLE_IN_THE_WALL":1,"DEFENDER":35,"MINI_WALLS":21,"ZOMBIES_BAD_BLOOD":10,"HIDE_AND_SEEK_PARTY_POOPER":19,"DAYONE":36,"GRINCH_SIMULATOR_V2":41,"DRAW_THEIR_THING":14,"ZOMBIES_ALIEN_ARCADIUM":40,"PVP_CTW":95,"ENDER":13,"STARWARS":2,"SANTA_SAYS":59,"DRAGONWARS2":8,"ZOMBIES_DEAD_END":154,"HIDE_AND_SEEK_PROP_HUNT":40,"FARM_HUNT":42}},"MCGO":{"players":86,"modes":{"normal":20,"deathmatch":49}},"SPEED_UHC":{"players":18,"modes":{"solo_normal":18}},"PROTOTYPE":{"players":442,"modes":{"PIXEL_PARTY":80,"INVADERS":39,"TOWERWARS_SOLO":31}},"SURVIVAL_GAMES":{"players":98,"modes":{"solo_normal":45,"teams_normal":22}},"BEDWARS":{"players":10205,"modes":{"BEDWARS_TWO_FOUR":636,"BEDWARS_FOUR_THREE":1137,"BEDWARS_FOUR_FOUR_LUCKY":2,"BEDWARS_EIGHT_ONE":1530,"BEDWARS_EIGHT_TWO_SWAP":234,"BEDWARS_EIGHT_TWO":2522,"BEDWARS_FOUR_FOUR":2204,"BEDWARS_PRACTICE":228,"BEDWARS_EIGHT_TWO_LUCKY":15,"BEDWARS_EIGHT_TWO_ULTIMATE":2,"BEDWARS_FOUR_FOUR_SWAP":284}},"PIT":{"players":142,"modes":{"PIT":142}},"REPLAY":{"players":38,"modes":{"BASE":38}},"SUPER_SMASH":{"players":41,"modes":{"1v1_normal":9,"solo_normal":1,"2v2_normal":8,"teams_normal":7}},"TNTGAMES":{"players":396,"modes":{"PVPRUN":3,"TNTAG":178,"TNTRUN":111,"CAPTURE":9,"BOWSPLEEF":22}},"BUILD_BATTLE":{"players":499,"modes":{"BUILD_BATTLE_SOLO_NORMAL_LATEST":132,"BUILD_BATTLE_GUESS_THE_BUILD":58,"BUILD_BATTLE_TEAMS_NORMAL":137,"BUILD_BATTLE_SOLO_NORMAL":77,"BUILD_BATTLE_SOLO_PRO":25,"BUILD_BATTLE_CHRISTMAS_NEW_SOLO":5}},"WALLS3":{"players":26,"modes":{"gvg":11}},"MURDER_MYSTERY":{"players":566,"modes":{"MURDER_DOUBLE_UP":135,"MURDER_INFECTION":72,"MURDER_ASSASSINS":19,"MURDER_CLASSIC":254}},"HOUSING":{"players":1448},"LIMBO":{"players":355},"IDLE":{"players":4686},"QUEUE":{"players":0}},"playerCount":42340}