{"success":true,"games":{"MAIN_LOBBY":{"players":1241},"TOURNAMENT_LOBBY":{"players":10},"MURDER_MYSTERY":{"players":820,"modes":{"MURDER_DOUBLE_UP":173,"MURDER_INFECTION":98,"MURDER_ASSASSINS":40,"MURDER_CLASSIC":371}},"LEGACY":{"players":164,"modes":{"VAMPIREZ":44,"WALLS":33,"PAINTBALL":32,"ARENA":4,"GINGERBREAD":7,"QUAKECRAFT":9}},"SURVIVAL_GAMES":{"players":178,"modes":{"solo_normal":75,"teams_normal":65}},"REPLAY":{"players":55,"modes":{"BASE":55}},"WALLS3":{"players":111,"modes":{"standard":85,"face_off":4}},"ARCADE":{"players":2133,"modes":{"PARTY":444,"HOLE_IN_THE_WALL":14,"DEFENDER":76,"MINI_WALLS":53,"SIMON_SAYS":46,"ZOMBIES_BAD_BLOOD":23,"HIDE_AND_SEEK_PARTY_POOPER":24,"DAYONE":75,"DRAW_THEIR_THING":25,"ZOMBIES_ALIEN_ARCADIUM":83,"ONEINTHEQUIVER":8,"SOCCER":23,"PVP_CTW":133,"ENDER":15,"STARWARS":18,"DRAGONWARS2":1,"ZOMBIES_DEAD_END":197,"HIDE_AND_SEEK_PROP_HUNT":61,"FARM_HUNT":43,"EASTER_SIMULATOR":515}},"BUILD_BATTLE":{"players":931,"modes":{"BUILD_BATTLE_SOLO_NORMAL_LATEST":249,"BUILD_BATTLE_GUESS_THE_BUILD":110,"BUILD_BATTLE_TEAMS_NORMAL":290,"BUILD_BATTLE_SOLO_NORMAL":138,"BUILD_BATTLE_SOLO_PRO":30}},"HOUSING":{"players":1421},"PROTOTYPE":{"players":333,"modes":{"TOWERWARS_SOLO":49,"TOWERWARS_TEAM_OF_TWO":21}},"SUPER_SMASH":{"players":40,"modes":{"1v1_normal":4,"solo_normal":11,"2v2_normal":9,"teams_normal":1}},"SKYWARS":{"players":3841,"modes":{"ranked_normal":231,"solo_insane_tnt_madness":56,"solo_insane_lucky":113,"teams_insane_lucky":89,"solo_normal":1067,"teams_insane":251,"solo_insane_hunters_vs_beasts":4,"solo_insane":906,"teams_insane_tnt_madness":12,"teams_normal":446}},"SKYBLOCK":{"players":30299,"modes":{"dungeon_hub":1020,"mining_2":795,"farming_2":181,"farming_1":98,"mining_3":1127,"combat_3":1005,"dynamic":12650,"combat_1":1243,"foraging_1":569,"hub":8667,"combat_2":175,"dungeon":2596,"mining_1":175}},"MCGO":{"players":107,"modes":{"normal":49,"deathmatch":36}},"UHC":{"players":544,"modes":{"TEAMS":311,"SOLO":174}},"BEDWARS":{"players":23181,"modes":{"BEDWARS_TWO_FOUR":843,"BEDWARS_FOUR_FOUR_RUSH":709,"BEDWARS_EIGHT_ONE":3222,"BEDWARS_EIGHT_TWO_VOIDLESS":13,"BEDWARS_EIGHT_TWO_RUSH":555,"BEDWARS_EIGHT_TWO_ARMED":7,"BEDWARS_FOUR_FOUR":4050,"BEDWARS_EIGHT_TWO":7034,"BEDWARS_FOUR_FOUR_ULTIMATE":2,"BEDWARS_EIGHT_TWO_LUCKY":20,"BEDWARS_PRACTICE":542,"BEDWARS_FOUR_THREE":3337,"BEDWARS_EIGHT_TWO_ULTIMATE":9}},"BATTLEGROUND":{"players":42,"modes":{"ctf_mini":24,"domination":5,"team_deathmatch":2}},"PIT":{"players":559,"modes":{"PIT":559}},"SPEED_UHC":{"players":61,"modes":{"team_normal":29,"solo_normal":32}},"TNTGAMES":{"players":598,"modes":{"PVPRUN":9,"TNTAG":274,"TNTRUN":184,"BOWSPLEEF":18,"CAPTURE":23}},"DUELS":{"players":3241,"modes":{"DUELS_BOWSPLEEF_DUEL":22,"DUELS_BRIDGE_2V2V2V2":5,"DUELS_BOW_DUEL":15,"DUELS_MW_DUEL":22,"DUELS_UHC_FOUR":70,"DUELS_UHC_MEETUP":48,"DUELS_BRIDGE_DOUBLES":116,"DUELS_SW_DOUBLES":103,"DUELS_UHC_DOUBLES":91,"DUELS_BRIDGE_FOUR":43,"DUELS_SUMO_DUEL":130,"DUELS_BRIDGE_3V3V3V3":16,"DUELS_UHC_DUEL":424,"DUELS_OP_DOUBLES":43,"DUELS_OP_DUEL":78,"DUELS_BLITZ_DUEL":57,"DUELS_POTION_DUEL":14,"DUELS_CLASSIC_DUEL":270,"DUELS_COMBO_DUEL":36,"DUELS_BRIDGE_DUEL":665,"DUELS_SW_DUEL":295}},"LIMBO":{"players":137},"IDLE":{"players":5510},"QUEUE":{"players":0}},"playerCount":75577}