{"success":true,"games":{"MAIN_LOBBY":{"players":345},"TOURNAMENT_LOBBY":{"players":10},"SMP":{"players":1116},"BEDWARS":{"players":18174,"modes":{"BEDWARS_FOUR_FOUR_VOIDLESS":298,"BEDWARS_TWO_FOUR":816,"BEDWARS_FOUR_THREE":2442,"BEDWARS_FOUR_FOUR_LUCKY":3,"BEDWARS_EIGHT_ONE":2424,"BEDWARS_EIGHT_TWO_VOIDLESS":217,"BEDWARS_EIGHT_TWO_ARMED":2,"BEDWARS_FOUR_FOUR":4034,"BEDWARS_EIGHT_TWO":5108,"BEDWARS_EIGHT_TWO_LUCKY":19,"BEDWARS_PRACTICE":399,"BEDWARS_EIGHT_TWO_ULTIMATE":8}},"UHC":{"players":380,"modes":{"TEAMS":209,"SOLO":125}},"WALLS3":{"players":157,"modes":{"standard":125}},"TNTGAMES":{"players":692,"modes":{"PVPRUN":11,"TNTAG":267,"TNTRUN":196,"CAPTURE":50,"BOWSPLEEF":39}},"LEGACY":{"players":170,"modes":{"WALLS":26,"ARENA":0,"QUAKECRAFT":22,"PAINTBALL":21,"VAMPIREZ":70,"GINGERBREAD":6}},"ARCADE":{"players":1518,"modes":{"PARTY":345,"HOLE_IN_THE_WALL":16,"DEFENDER":48,"MINI_WALLS":30,"SIMON_SAYS":47,"ZOMBIES_BAD_BLOOD":32,"HIDE_AND_SEEK_PARTY_POOPER":38,"DAYONE":92,"DRAW_THEIR_THING":28,"ZOMBIES_ALIEN_ARCADIUM":104,"SOCCER":22,"PVP_CTW":125,"THROW_OUT":16,"ENDER":1,"STARWARS":18,"ZOMBIES_DEAD_END":191,"HIDE_AND_SEEK_PROP_HUNT":79,"FARM_HUNT":70}},"SURVIVAL_GAMES":{"players":146,"modes":{"solo_normal":59,"teams_normal":50}},"PIT":{"players":481,"modes":{"PIT":481}},"SKYWARS":{"players":2702,"modes":{"ranked_normal":111,"solo_insane_tnt_madness":7,"solo_insane_slime":53,"teams_insane_slime":12,"solo_insane_rush":29,"solo_normal":776,"teams_insane":209,"solo_insane":766,"teams_normal":247}},"REPLAY":{"players":58,"modes":{"BASE":58}},"SUPER_SMASH":{"players":35,"modes":{"1v1_normal":2,"solo_normal":4,"2v2_normal":12,"teams_normal":1}},"PROTOTYPE":{"players":393,"modes":{"TOWERWARS_SOLO":44,"TOWERWARS_TEAM_OF_TWO":22}},"MURDER_MYSTERY":{"players":941,"modes":{"MURDER_DOUBLE_UP":249,"MURDER_INFECTION":79,"MURDER_ASSASSINS":66,"MURDER_CLASSIC":418}},"MCGO":{"players":87,"modes":{"normal":32,"deathmatch":35}},"BUILD_BATTLE":{"players":914,"modes":{"BUILD_BATTLE_SOLO_NORMAL_LATEST":212,"BUILD_BATTLE_GUESS_THE_BUILD":98,"BUILD_BATTLE_TEAMS_NORMAL":304,"BUILD_BATTLE_SOLO_PRO":51,"BUILD_BATTLE_SOLO_NORMAL":160}},"HOUSING":{"players":1766},"SKYBLOCK":{"players":25207,"modes":{"dungeon_hub":910,"farming_1":314,"mining_2":689,"mining_3":1313,"combat_3":1456,"crystal_hollows":1181,"dynamic":9765,"combat_1":431,"foraging_1":536,"hub":5998,"combat_2":178,"dungeon":2305,"mining_1":134}},"SPEED_UHC":{"players":58,"modes":{"team_normal":33,"solo_normal":25}},"DUELS":{"players":3387,"modes":{"DUELS_BOWSPLEEF_DUEL":29,"DUELS_BRIDGE_2V2V2V2":7,"DUELS_BOW_DUEL":14,"DUELS_UHC_FOUR":61,"DUELS_MW_DUEL":12,"DUELS_UHC_MEETUP":37,"DUELS_BRIDGE_DOUBLES":220,"DUELS_SW_DOUBLES":71,"DUELS_UHC_DOUBLES":37,"DUELS_BRIDGE_FOUR":119,"DUELS_BRIDGE_3V3V3V3":3,"DUELS_SUMO_DUEL":193,"DUELS_UHC_DUEL":363,"DUELS_OP_DOUBLES":27,"DUELS_OP_DUEL":50,"DUELS_BLITZ_DUEL":40,"DUELS_POTION_DUEL":9,"DUELS_CLASSIC_DUEL":250,"DUELS_COMBO_DUEL":26,"DUELS_BRIDGE_DUEL":956,"DUELS_SW_DUEL":214}},"BATTLEGROUND":{"players":128,"modes":{"ctf_mini":61,"team_deathmatch":27}},"LIMBO":{"players":252},"IDLE":{"players":5981},"QUEUE":{"players":0}},"playerCount":64988}