{"success":true,"games":{"MAIN_LOBBY":{"players":275},"TOURNAMENT_LOBBY":{"players":10},"SMP":{"players":943},"LEGACY":{"players":85,"modes":{"VAMPIREZ":45,"ARENA":0,"GINGERBREAD":3,"QUAKECRAFT":4,"PAINTBALL":13,"WALLS":3}},"SUPER_SMASH":{"players":24,"modes":{"1v1_normal":7,"solo_normal":4}},"DUELS":{"players":1617,"modes":{"DUELS_BOWSPLEEF_DUEL":22,"DUELS_BRIDGE_2V2V2V2":7,"DUELS_BOW_DUEL":19,"DUELS_UHC_FOUR":1,"DUELS_MW_DUEL":20,"DUELS_BRIDGE_DOUBLES":103,"DUELS_SW_DOUBLES":26,"DUELS_BOXING_DUEL":17,"DUELS_UHC_DOUBLES":25,"DUELS_BRIDGE_FOUR":8,"DUELS_SUMO_DUEL":64,"DUELS_UHC_DUEL":152,"DUELS_OP_DOUBLES":7,"DUELS_BRIDGE_THREES":24,"DUELS_PARKOUR_EIGHT":72,"DUELS_OP_DUEL":32,"DUELS_MW_DOUBLES":7,"DUELS_BLITZ_DUEL":34,"DUELS_DUEL_ARENA":9,"DUELS_POTION_DUEL":2,"DUELS_CLASSIC_DUEL":108,"DUELS_COMBO_DUEL":28,"DUELS_BRIDGE_DUEL":393,"DUELS_SW_DUEL":111}},"PIT":{"players":161,"modes":{"PIT":161}},"WOOL_GAMES":{"players":379,"modes":{"wool_wars_two_four":295}},"REPLAY":{"players":75,"modes":{"BASE":75}},"SKYBLOCK":{"players":23484,"modes":{"instanced":32,"dungeon_hub":1006,"farming_1":251,"mining_2":480,"crimson_isle":1597,"mining_3":1358,"combat_3":1255,"dynamic":7883,"crystal_hollows":1234,"combat_1":319,"foraging_1":531,"hub":4914,"dungeon":2513,"mining_1":109}},"SURVIVAL_GAMES":{"players":93,"modes":{"solo_normal":34,"teams_normal":36}},"SPEED_UHC":{"players":13,"modes":{"solo_normal":13}},"BUILD_BATTLE":{"players":536,"modes":{"BUILD_BATTLE_SOLO_NORMAL_LATEST":165,"BUILD_BATTLE_GUESS_THE_BUILD":64,"BUILD_BATTLE_TEAMS_NORMAL":140,"BUILD_BATTLE_SOLO_PRO":33,"BUILD_BATTLE_SOLO_NORMAL":74}},"PROTOTYPE":{"players":286,"modes":{"PIXEL_PARTY":31}},"TNTGAMES":{"players":306,"modes":{"TNTAG":147,"TNTRUN":81,"BOWSPLEEF":16,"CAPTURE":14}},"MCGO":{"players":71,"modes":{"normal":42,"deathmatch":9}},"HOUSING":{"players":1292},"BEDWARS":{"players":8688,"modes":{"BEDWARS_TWO_FOUR":558,"BEDWARS_FOUR_THREE":966,"BEDWARS_EIGHT_ONE":1168,"BEDWARS_FOUR_FOUR_ARMED":446,"BEDWARS_EIGHT_TWO_ARMED":266,"BEDWARS_FOUR_FOUR":1823,"BEDWARS_EIGHT_TWO":2110,"BEDWARS_EIGHT_TWO_LUCKY":15,"BEDWARS_PRACTICE":165,"BEDWARS_EIGHT_TWO_ULTIMATE":2}},"MURDER_MYSTERY":{"players":591,"modes":{"MURDER_DOUBLE_UP":145,"MURDER_INFECTION":77,"MURDER_ASSASSINS":40,"MURDER_CLASSIC":235}},"UHC":{"players":297,"modes":{"TEAMS":175,"SOLO":88}},"WALLS3":{"players":17},"SKYWARS":{"players":1225,"modes":{"ranked_normal":57,"teams_insane":82,"solo_normal":415,"solo_insane":316,"teams_normal":121,"mega_normal":6}},"ARCADE":{"players":813,"modes":{"PARTY":176,"DEFENDER":23,"SIMON_SAYS":21,"ZOMBIES_BAD_BLOOD":19,"HIDE_AND_SEEK_PARTY_POOPER":17,"DAYONE":40,"DRAW_THEIR_THING":12,"ZOMBIES_ALIEN_ARCADIUM":64,"SOCCER":19,"PVP_CTW":45,"STARWARS":1,"ZOMBIES_DEAD_END":174,"FARM_HUNT":32,"HIDE_AND_SEEK_PROP_HUNT":48}},"BATTLEGROUND":{"players":10,"modes":{"ctf_mini":9}},"LIMBO":{"players":258},"IDLE":{"players":4134},"QUEUE":{"players":0}},"playerCount":45672}